shipdataprocess/__init__.py
shipdataprocess/_version.py
shipdataprocess/collapse.py
shipdataprocess/normalize.py
shipdataprocess/shiptype.py
shipdataprocess/standardize.py
shipdataprocess-0.8.6.dist-info/LICENSE
shipdataprocess-0.8.6.dist-info/METADATA
shipdataprocess-0.8.6.dist-info/WHEEL
shipdataprocess-0.8.6.dist-info/top_level.txt
shipdataprocess-0.8.6.dist-info/zip-safe
shipdataprocess-0.8.6.dist-info/RECORD
