Metadata-Version: 2.1
Name: shipdataprocess
Version: 0.8.6
Summary: Useful modules to process vessel data
Home-page: https://github.com/GlobalFishingWatch/shipdataprocess
Author: Jaeyoon Park
Author-email: jaeyoon@globalfishingwatch.org
License: Apache 2.0
Keywords: ship,vessel,fishing,normalization
Platform: UNKNOWN
Requires-Python: >=3.6
License-File: LICENSE
Requires-Dist: pytest
Requires-Dist: unidecode
Requires-Dist: roman
Provides-Extra: test
Requires-Dist: pytest ; extra == 'test'
